meteoalertapi/__init__.py
meteoalertapi/meteoalertapi.py
meteoalertapi-0.3.1.dist-info/LICENSE
meteoalertapi-0.3.1.dist-info/METADATA
meteoalertapi-0.3.1.dist-info/WHEEL
meteoalertapi-0.3.1.dist-info/top_level.txt
meteoalertapi-0.3.1.dist-info/RECORD
