Metadata-Version: 2.1
Name: meteoalertapi
Version: 0.3.1
Summary: A small api to get alerting messages from extreme weather in Europe from https://www.meteoalarm.org.
Home-page: https://github.com/rolfberkenbosch/meteoalert-api
Author: Rolf Berkenbosch
Author-email: rolf@berkenbosch.nl
License: MIT
Classifier: Programming Language :: Python :: 3
Classifier: License :: OSI Approved :: MIT License
Classifier: Operating System :: OS Independent
License-File: LICENSE
Requires-Dist: xmltodict
Requires-Dist: requests
